{" * --delay 20 --cronid 1 1>* 2>&1": 0, "*": 1, "* >> * 2>&1": 2, "run-parts *": 3, "(*) starting 0anacron": 4, "Anacron started on 2024-04-18": 5, "Normal exit (*)": 6, "(*) finished 0anacron": 7, "* \"STATUS_CHECK\" -p local2.info >> *": 8, " * --delay 20 --cronid 2 1>* 2>&1": 9, " * 239m * g  >*  2>&1": 10, "* 1>* 2>*": 11, "source *; python * -p $(date +%Y%m%d": 12, "Will run job `cron.daily' in 45 min.": 13, "Jobs will be executed sequentially": 14, "Job `cron.daily' started": 15, "(*) starting logrotate": 16, "(*) finished logrotate": 17, "Job `cron.daily' terminated": 18, "[ ! -s * ] && * 's*/' * > *": 19, "* -m rpm -a >* 2>&1": 20, ". *; . *; module load python*; ${HOME}* --cluster ${HOME}* --path_statistics ${HOME}* --path_account ${HOME}* --path_raw ${HOME}*/": 21, "source *; python * -p $(date -d \"yesterday\" +%Y%m%d": 22, "*: uid=0 from=*": 23, "*: *": 24, "*: from=*, size=*, nrcpt=* (*)": 25, "*: to=*, *, *, *, **, *, status=status=*": 26, "*: removed": 27, "*: uid=35148 from=*": 28, "*: uid=12542 from=*": 29, "*: sender non-delivery notification: *": 30, "*: to=*, *, *, **, *, status=status=*": 31, "Started Update a database for mlocate.": 32, "Starting update of the root trust anchor for DNSSEC validation in unbound...": 33, "unbound-anchor.service: Succeeded.": 34, "Started update of the root trust anchor for DNSSEC validation in unbound.": 35, "Created slice User Slice of *.": 36, "Started * mount wrapper.": 37, "Starting User Manager for *...": 38, "Started session * of user *.": 39, "Starting D-Bus User Message Bus Socket.": 40, "Reached target Paths.": 41, "Started Mark boot as successful after the user * has run 2 minutes.": 42, "Reached target Timers.": 43, "Listening on D-Bus User Message Bus Socket.": 44, "Reached target Sockets.": 45, "Reached target Basic System.": 46, "Reached target Default.": 47, "Startup finished in 34ms.": 48, "Started User Manager for *.": 49, "mlocate-updatedb.service: Succeeded.": 50, "New session * of user *.": 51, "session * logged out. Waiting for processes to exit.": 52, "session *.scope: Succeeded.": 53, "Removed session *.": 54, "Stopping User Manager for *...": 55, "Stopped target Default.": 56, "Stopped target Basic System.": 57, "Stopped target Sockets.": 58, "Stopped target Timers.": 59, "grub-boot-success.timer: Succeeded.": 60, "Stopped Mark boot as successful after the user * has run 2 minutes.": 61, "Stopped target Paths.": 62, "dbus.socket: Succeeded.": 63, "Closed D-Bus User Message Bus Socket.": 64, "Reached target Shutdown.": 65, "Starting Exit the Session...": 66, "user@12542.service: Succeeded.": 67, "Stopped User Manager for *.": 68, "Stopping * mount wrapper...": 69, "Removed slice User Slice of *.": 70, "run-user-12542.mount: Succeeded.": 71, "user-runtime-dir@12542.service: Succeeded.": 72, "Stopped * mount wrapper.": 73, "Startup finished in 32ms.": 74, "user@12546.service: Succeeded.": 75, "run-user-12546.mount: Succeeded.": 76, "user-runtime-dir@12546.service: Succeeded.": 77, "user@12503.service: Succeeded.": 78, "run-user-12503.mount: Succeeded.": 79, "user-runtime-dir@12503.service: Succeeded.": 80, "Startup finished in 31ms.": 81, "Startup finished in 33ms.": 82, "user@12571.service: Succeeded.": 83, "run-user-12571.mount: Succeeded.": 84, "user-runtime-dir@12571.service: Succeeded.": 85, "user@126858.service: Succeeded.": 86, "run-user-126858.mount: Succeeded.": 87, "user-runtime-dir@126858.service: Succeeded.": 88, "NOTICE [sshd] Unban *": 89, "INFO [sshd] Found * - 2024-04-18 00:00:34": 90, "INFO [sshd] Found * - 2024-04-18 00:00:36": 91, "INFO [sshd] Found * - 2024-04-18 00:01:20": 92, "INFO [sshd] Found * - 2024-04-18 00:01:23": 93, "NOTICE [sshd] Ban *": 94, "INFO [sshd] Found * - 2024-04-18 00:01:39": 95, "pam_unix(*): session * for user * by (*)": 96, "Accepted publickey for * from * port * ssh2: RSA **": 97, "Received disconnect from * port *:11: disconnected by user": 98, "Disconnected from user * * port *": 99, "pam_unix(*): session * for user *": 100, "ganglia : TTY=unknown ; PWD=/ ; USER=root ; COMMAND=*": 101, "Accepted publickey for * from * port * ssh2: RSA *": 102, "Received disconnect from * port *:11: Shutdown": 103, "Accepted publickey for * from * port * ssh2: RSA *+0kCLlFY2n6Coli0UI8aWqY5g": 104, "Invalid user * from * port *": 105, "pam_unix(*): check pass; user *": 106, "pam_unix(*): authentication failure; logname= uid=0 euid=0 tty=ssh ruser= rhost=77-61-64-143.biz.kpn.net": 107, "Failed password for invalid user * from * port * ssh2": 108, "Received disconnect from * port *:11: Bye Bye [preauth]": 109, "Disconnected from invalid user * * port * [preauth]": 110, "pam_unix(*): authentication failure; logname= uid=0 euid=0 tty=ssh ruser= rhost=*": 111, "pam_unix(*): authentication failure; logname= uid=0 euid=0 tty=ssh ruser= rhost=77-61-64-143.biz.kpn.net  user=root": 112, "Failed password for root from * port * ssh2": 113, "Disconnected from authenticating user * * port * [preauth]": 114, "Connection closed by * port * [preauth]": 115, "Address * maps to dynamic-adsl.viettel.vn, but this does not map back to the address.": 116, "pam_unix(*): authentication failure; logname= uid=0 euid=0 tty=ssh ruser= rhost=*  user=root": 117, "Address * maps to dynamic-ip-adsl.viettel.vn, but this does not map back to the address.": 118, "pam_unix(*): authentication failure; logname= uid=0 euid=0 tty=ssh ruser= rhost=189-50-97-135-wlan.lpnet.com.br": 119, "reverse mapping checking getaddrinfo for hn.kd.smx.adsl [*] failed.": 120, "reverse mapping checking getaddrinfo for 177-131-18-74.webflash.net.br [*] failed.": 121, "Invalid user *_user * * port *": 122, "Failed password for invalid user *_user * * port * ssh2": 123, "Received disconnect from * port *:11: Bye [preauth]": 124, "Timeout, client not responding from user * * port *": 125, "Received disconnect from * port *:11:  [preauth]": 126, "PAM 1 more authentication failure; logname= uid=0 euid=0 tty=ssh ruser= rhost=*  user=root": 127, "Package *": 128, "Signature archive *": 129, "Manifest *": 130, "Signature *": 131, "ManifestPackageIntegrityPolicy succeeded.": 132, "SignatureIntegrityPolicy for primary signature succeeded.": 133, "SignatureValidityPolicy for primary signature succeeded.": 134, "SignatureIntegrityPolicy for primary timestamp signature succeeded.": 135, "SignatureValidityPolicy for primary timestamp signature succeeded.": 136, "X.509 certificate chain validation will use the fallback certificate bundle for timestamping.": 137, "SignatureTrustPolicy for repository primary signature timestamp signature succeeded.": 138, "X.509 certificate chain validation will use the fallback certificate bundle for code signing.": 139, "SignatureTrustPolicy for repository primary signature succeeded.": 140, "RepositoryCountersignaturePolicy for repository primary signature succeeded.": 141, "Primary signature type:  repository primary signature": 142, "Primary signature status:  OK": 143, "Timestamp signature status:  OK": 144, "Exit code:  Success": 145, "Process * (*) of user * dumped core.": 146, " * --delay 21 --cronid 1 1>* 2>&1": 147, ". *; . ~*; cd ~*; python3 sinfo.py": 148, " * --delay 21 --cronid 2 1>* 2>&1": 149, "Will run job `cron.daily' in 9 min.": 150, "Will run job `cron.weekly' in 29 min.": 151, "Job `cron.weekly' started": 152, "Job `cron.weekly' terminated": 153, "*: uid=12563 from=*": 154, "Startup finished in 36ms.": 155, "user@12563.service: Succeeded.": 156, "run-user-12563.mount: Succeeded.": 157, "user-runtime-dir@12563.service: Succeeded.": 158, "Connection reset by invalid user * * port * [preauth]": 159, "Connection closed by invalid user * * port * [preauth]": 160, "Accepted publickey for * from * port * * ** *.com (*) CA ECDSA *": 161, "Connection closed by authenticating user * * port * [preauth]": 162, "Accepted publickey for * from * port * * *+Z0rHx1GPPLLnesIDH8 *.com (*) CA ECDSA *": 163, "PAM 2 more authentication failures; logname= uid=0 euid=0 tty=ssh ruser= rhost=*  user=root": 164, "error: kex_exchange_identification: read: Connection reset by peer": 165, "reverse mapping checking getaddrinfo for ppp-52-198.32-151.wind.it [*] failed.": 166, "Accepted publickey for * from * port * * *+kLnPICaSLmChnIjN0K+HrJSR0lpI9JNoHhUo * (*) CA ECDSA *": 167, " * --delay 22 --cronid 1 1>* 2>&1": 168, " * --delay 22 --cronid 2 1>* 2>&1": 169, "Will run job `cron.daily' in 22 min.": 170, "*: uid=33683 from=*": 171, "slurmd: slurmd_req: received opcode REQUEST_ACCT_GATHER_UPDATE from *:55872 uid 6003": 172, "slurmd_req: received opcode REQUEST_ACCT_GATHER_UPDATE from *:55872 uid 6003": 173, "user@125778.service: Succeeded.": 174, "run-user-125778.mount: Succeeded.": 175, "user-runtime-dir@125778.service: Succeeded.": 176, "slurmd: slurmd_req: received opcode REQUEST_ACCT_GATHER_UPDATE from *:56114 uid 6003": 177, "slurmd_req: received opcode REQUEST_ACCT_GATHER_UPDATE from *:56114 uid 6003": 178, "slurmd: slurmd_req: received opcode REQUEST_HEALTH_CHECK from *:56154 uid 6003": 179, "slurmd_req: received opcode REQUEST_HEALTH_CHECK from *:56154 uid 6003": 180, "Connection reset by * port * [preauth]": 181, "error: kex_exchange_identification: Connection closed by remote host": 182, "Connection reset by invalid user * *.159.163.6 port * [preauth]": 183, " * --delay 29 --cronid 2 1>* 2>&1": 184, " * --delay 29 --cronid 1 1>* 2>&1": 185, " * --delay 29 --cronid 3 1>* 2>&1": 186, " * --delay 29 --cronid 4 1>* 2>&1": 187, "Will run job `cron.weekly' in 62 min.": 188, "Job `cron.weekly' locked by another anacron - skipping": 189, "Will run job `cron.daily' in 36 min.": 190, "6BE563AD: uid=0 from=*": 191, "6BE563AD: *": 192, "6BE563AD: from=*, size=*, nrcpt=* (*)": 193, "6BE563AD: to=*, *, *, *, **, *, status=status=*": 194, "6BE563AD: removed": 195, "C718F19862: uid=0 from=*": 196, "C718F19862: *": 197, "C718F19862: from=*, size=*, nrcpt=* (*)": 198, "C718F19862: to=*, *, *, *, **, *, status=status=*": 199, "C718F19862: removed": 200, "Startup finished in 38ms.": 201, "user@0.service: Succeeded.": 202, "run-user-0.mount: Succeeded.": 203, "user-runtime-dir@0.service: Succeeded.": 204, "slurmd: slurmd_req: received opcode REQUEST_ACCT_GATHER_UPDATE from *:34234 uid 6003": 205, "slurmd_req: received opcode REQUEST_ACCT_GATHER_UPDATE from *:34234 uid 6003": 206, "notice: State transition S_IDLE -> S_POLICY_ENGINE": 207, "notice: On loss of quorum: Ignore": 208, "notice: Calculated transition 5350, saving inputs in *": 209, "notice: Transition 5350 (*): Complete": 210, "notice: State transition S_TRANSITION_ENGINE -> S_IDLE": 211, "Startup finished in 35ms.": 212, "slurmd: slurmd_req: received opcode REQUEST_ACCT_GATHER_UPDATE from *:34554 uid 6003": 213, "slurmd_req: received opcode REQUEST_ACCT_GATHER_UPDATE from *:34554 uid 6003": 214, "slurmd: slurmd_req: received opcode REQUEST_HEALTH_CHECK from *:42218 uid 6003": 215, "slurmd_req: received opcode REQUEST_HEALTH_CHECK from *:42218 uid 6003": 216, "INFO [sshd] Found * - 2024-04-18 00:02:55": 217, "INFO [sshd] Found * - 2024-04-18 00:02:57": 218, "INFO [sshd] Found * - 2024-04-18 00:03:03": 219, "INFO [sshd] Found * - 2024-04-18 00:03:06": 220, "slurmd: slurmd_req: received opcode REQUEST_ACCT_GATHER_UPDATE from *:35052 uid 6003": 221, "slurmd_req: received opcode REQUEST_ACCT_GATHER_UPDATE from *:35052 uid 6003": 222, "slurmd: slurmd_req: received opcode REQUEST_PING from *:35152 uid 6003": 223, "slurmd_req: received opcode REQUEST_PING from *:35152 uid 6003": 224, "INFO [sshd] Found * - 2024-04-18 00:03:51": 225, "INFO [sshd] Found * - 2024-04-18 00:03:53": 226, "INFO [sshd] Found * - 2024-04-18 00:03:57": 227, "Audit daemon rotating log files": 228, "slurmd: slurmd_req: received opcode REQUEST_ACCT_GATHER_UPDATE from *:35454 uid 6003": 229, "slurmd_req: received opcode REQUEST_ACCT_GATHER_UPDATE from *:35454 uid 6003": 230, "INFO [sshd] Found * - 2024-04-18 00:05:04": 231, "INFO [sshd] Found * - 2024-04-18 00:05:06": 232, "slurmd: slurmd_req: received opcode REQUEST_ACCT_GATHER_UPDATE from *:35752 uid 6003": 233, "slurmd_req: received opcode REQUEST_ACCT_GATHER_UPDATE from *:35752 uid 6003": 234, "slurmd: slurmd_req: received opcode REQUEST_ACCT_GATHER_UPDATE from *:36064 uid 6003": 235, "slurmd_req: received opcode REQUEST_ACCT_GATHER_UPDATE from *:36064 uid 6003": 236, "slurmd: slurmd_req: received opcode REQUEST_ACCT_GATHER_UPDATE from *:36382 uid 6003": 237, "slurmd_req: received opcode REQUEST_ACCT_GATHER_UPDATE from *:36382 uid 6003": 238, "slurmd: slurmd_req: received opcode REQUEST_HEALTH_CHECK from *:44218 uid 6003": 239, "slurmd_req: received opcode REQUEST_HEALTH_CHECK from *:44218 uid 6003": 240, "INFO [sshd] Found * - 2024-04-18 00:09:09": 241, "INFO [sshd] Found * - 2024-04-18 00:09:13": 242, "slurmd: slurmd_req: received opcode REQUEST_ACCT_GATHER_UPDATE from *:36872 uid 6003": 243, "slurmd_req: received opcode REQUEST_ACCT_GATHER_UPDATE from *:36872 uid 6003": 244, "slurmd: slurmd_req: received opcode REQUEST_PING from *:36978 uid 6003": 245, "slurmd_req: received opcode REQUEST_PING from *:36978 uid 6003": 246, "slurmd: slurmd_req: received opcode REQUEST_ACCT_GATHER_UPDATE from *:37276 uid 6003": 247, "slurmd_req: received opcode REQUEST_ACCT_GATHER_UPDATE from *:37276 uid 6003": 248, "Invalid user *qwaszx from * port *": 249, "pam_unix(*): authentication failure; logname= uid=0 euid=0 tty=ssh ruser= rhost=c-0762e455.02-129-6c6b7013.bbcust.telenor.se": 250, "Failed password for invalid user *qwaszx from * port * ssh2": 251, "Connection closed by invalid user *qwaszx * port * [preauth]": 252, "Anacron started on 2024-04-20": 253, "Will run job `cron.daily' in 46 min.": 254, "Startup finished in 39ms.": 255, "Startup finished in 43ms.": 256, "INFO [sshd] Found * - 2024-04-20 00:00:12": 257, "INFO [sshd] Found * - 2024-04-20 00:00:13": 258, "INFO [sshd] Found * - 2024-04-20 00:00:15": 259, "INFO [sshd] Found * - 2024-04-20 00:00:17": 260, "INFO [sshd] Found * - 2024-04-20 00:00:19": 261, "INFO [sshd] Found * - 2024-04-20 00:00:21": 262, "INFO [sshd] Found * - 2024-04-20 00:00:22": 263, "INFO [sshd] Found * - 2024-04-20 00:00:23": 264, "INFO [sshd] Found * - 2024-04-20 00:00:38": 265, "INFO [sshd] Found * - 2024-04-20 00:00:42": 266, "INFO [sshd] Found * - 2024-04-20 00:00:45": 267, "INFO [sshd] Found * - 2024-04-20 00:00:56": 268, "INFO [sshd] Found * - 2024-04-20 00:01:11": 269, "Disconnected from invalid user * *.2.65.174 port * [preauth]": 270, "pam_unix(*): authentication failure; logname= uid=0 euid=0 tty=ssh ruser= rhost=vps-d3f0d651.vps.ovh.net": 271, "reverse mapping checking getaddrinfo for 111-230-139-186.fibertel.com.ar [*] failed.": 272, "Disconnected from invalid user * *.139.230.111 port * [preauth]": 273, "Disconnected from invalid user * *.94.26.113 port * [preauth]": 274, "Disconnected from invalid user * *.221.48.115 port * [preauth]": 275, "pam_systemd(*): Failed to create session: Start job for unit user@12571.service failed with 'failed'": 276, "Will run job `cron.daily' in 17 min.": 277, "INFO [sshd] Found * - 2024-04-20 00:01:06": 278, "INFO [sshd] Found * - 2024-04-20 00:01:09": 279, "slurmd: slurmd_req: received opcode REQUEST_ACCT_GATHER_UPDATE from *:60238 uid 6003": 280, "slurmd_req: received opcode REQUEST_ACCT_GATHER_UPDATE from *:60238 uid 6003": 281, "INFO [sshd] Found * - 2024-04-20 00:00:32": 282, "INFO [sshd] Found * - 2024-04-20 00:00:37": 283, "slurmd: slurmd_req: received opcode REQUEST_PING from *:60340 uid 6003": 284, "slurmd_req: received opcode REQUEST_PING from *:60340 uid 6003": 285, "INFO [sshd] Found * - 2024-04-20 00:00:41": 286, "slurmd: slurmd_req: received opcode REQUEST_ACCT_GATHER_UPDATE from *:60630 uid 6003": 287, "slurmd_req: received opcode REQUEST_ACCT_GATHER_UPDATE from *:60630 uid 6003": 288, "INFO [sshd] Found * - 2024-04-20 00:01:23": 289, "LNetError: 55992:0:(*)) no route to *@tcp from <?>": 290, "LNetError: 55992:0:(*)) Skipped 2 previous similar messages": 291, "slurmd: slurmd_req: received opcode REQUEST_HEALTH_CHECK from *:60734 uid 6003": 292, "slurmd_req: received opcode REQUEST_HEALTH_CHECK from *:60734 uid 6003": 293, "INFO [sshd] Found * - 2024-04-20 00:02:42": 294, "INFO [sshd] Found * - 2024-04-20 00:02:45": 295, "Will run job `cron.daily' in 41 min.": 296, "B18AF19862: uid=0 from=*": 297, "B18AF19862: *": 298, "B18AF19862: from=*, size=*, nrcpt=* (*)": 299, "B18AF19862: to=*, *, *, *, **, *, status=status=*": 300, "B18AF19862: removed": 301, "A0FFF2EAFE: uid=0 from=*": 302, "A0FFF2EAFE: *": 303, "A0FFF2EAFE: from=*, size=*, nrcpt=* (*)": 304, "A0FFF2EAFE: to=*, *, *, *, **, *, status=status=*": 305, "A0FFF2EAFE: removed": 306, "Startup finished in 37ms.": 307, "slurmd: slurmd_req: received opcode REQUEST_ACCT_GATHER_UPDATE from *:59618 uid 6003": 308, "slurmd_req: received opcode REQUEST_ACCT_GATHER_UPDATE from *:59618 uid 6003": 309, "slurmd: slurmd_req: received opcode REQUEST_PING from *:59728 uid 6003": 310, "slurmd_req: received opcode REQUEST_PING from *:59728 uid 6003": 311, "notice: Calculated transition 5542, saving inputs in *": 312, "notice: Transition 5542 (*): Complete": 313, "slurmd: slurmd_req: received opcode REQUEST_ACCT_GATHER_UPDATE from *:59844 uid 6003": 314, "slurmd_req: received opcode REQUEST_ACCT_GATHER_UPDATE from *:59844 uid 6003": 315, "slurmd: slurmd_req: received opcode REQUEST_HEALTH_CHECK from *:46798 uid 6003": 316, "slurmd_req: received opcode REQUEST_HEALTH_CHECK from *:46798 uid 6003": 317, "INFO [sshd] Found * - 2024-04-20 00:02:33": 318, "INFO [sshd] Found * - 2024-04-20 00:02:37": 319, "INFO [sshd] Found * - 2024-04-20 00:02:40": 320, "INFO [sshd] Found * - 2024-04-20 00:02:50": 321, "INFO [sshd] Found * - 2024-04-20 00:02:52": 322, "slurmd: slurmd_req: received opcode REQUEST_ACCT_GATHER_UPDATE from *:59998 uid 6003": 323, "slurmd_req: received opcode REQUEST_ACCT_GATHER_UPDATE from *:59998 uid 6003": 324, "INFO [sshd] Found * - 2024-04-20 00:03:46": 325, "INFO [sshd] Found * - 2024-04-20 00:03:48": 326, "LNetError: 45239:0:(*)) no route to *@tcp from <?>": 327, "LNetError: 45239:0:(*)) Skipped 2 previous similar messages": 328, "slurmd: slurmd_req: received opcode REQUEST_ACCT_GATHER_UPDATE from *:60122 uid 6003": 329, "slurmd_req: received opcode REQUEST_ACCT_GATHER_UPDATE from *:60122 uid 6003": 330, "[13107675.batch] task 0 (*) exited with exit code 0.": 331, "[13107675.batch] task*: task_cgroup_memory_check_oom: StepId=13107675.batch hit memory+swap limit at least once during execution. This may or may not result in some failure.": 332, "[13107675.batch] job 13107675 completed with slurm_rc = 0, job_rc = 0": 333, "[13107675.batch] PROTOCOL: sending REQUEST_COMPLETE_BATCH_SCRIPT slurm_rc:No error job_rc:0": 334, "[13107675.batch] done with step": 335, "slurmd: slurmd_req: received opcode REQUEST_TERMINATE_JOB from *:48454 uid 6003": 336, "slurmd_req: received opcode REQUEST_TERMINATE_JOB from *:48454 uid 6003": 337, "[13107675.extern] Sent signal 18 to StepId=13107675.extern": 338, "[13107675.extern] Sent signal 15 to StepId=13107675.extern": 339, "[13107675.extern] task*: task_cgroup_memory_check_oom: StepId=13107675.extern hit memory+swap limit at least once during execution. This may or may not result in some failure.": 340, "[13107675.extern] done with step": 341, "slurmd: slurmd_req: received opcode REQUEST_LAUNCH_PROLOG from *:48462 uid 6003": 342, "slurmd_req: received opcode REQUEST_LAUNCH_PROLOG from *:48462 uid 6003": 343, "slurmd: slurmd_req: received opcode REQUEST_BATCH_JOB_LAUNCH from *:48464 uid 6003": 344, "slurmd_req: received opcode REQUEST_BATCH_JOB_LAUNCH from *:48464 uid 6003": 345, "task*: task_p_slurmd_batch_request: task_p_slurmd_batch_request: 13107679": 346, "slurmd: task*: task_p_slurmd_batch_request: task_p_slurmd_batch_request: 13107679": 347, "slurmd: task*: batch_bind: job 13107679 CPU input mask for node: 0x000000000008": 348, "slurmd: task*: batch_bind: job 13107679 CPU final HW mask for node: 0x000000000040": 349, "task*: batch_bind: job 13107679 CPU input mask for node: 0x000000000008": 350, "task*: batch_bind: job 13107679 CPU final HW mask for node: 0x000000000040": 351, "[13107679.extern] task*: init: task affinity plugin loaded with CPU mask 0x333333333333": 352, "[13107679.extern] topology*: init: topology tree plugin loaded": 353, "[13107679.extern] task*: _memcg_initialize: job: alloc=10240MB mem.limit=10240MB memsw.limit=10240MB job_swappiness=18446744073709551614": 354, "[13107679.extern] task*: _memcg_initialize: step: alloc=10240MB mem.limit=10240MB memsw.limit=10240MB job_swappiness=18446744073709551614": 355, "slurmd: Launching batch job 13107679 for *": 356, "Launching batch job 13107679 for *": 357, "[13107679.batch] task*: init: task affinity plugin loaded with CPU mask 0x333333333333": 358, "[13107679.batch] topology*: init: topology tree plugin loaded": 359, "[13107679.batch] task*: _memcg_initialize: job: alloc=10240MB mem.limit=10240MB memsw.limit=10240MB job_swappiness=18446744073709551614": 360, "[13107679.batch] task*: _memcg_initialize: step: alloc=10240MB mem.limit=10240MB memsw.limit=10240MB job_swappiness=18446744073709551614": 361, "[13107679.batch] debug levels are stderr='error', logfile='verbose', syslog='verbose'": 362, "[13107679.batch] starting 1 tasks": 363, "[13107679.batch] task 0 (*) started 2024-04-20T00:04:33": 364, "slurmd: slurmd_req: received opcode REQUEST_ACCT_GATHER_UPDATE from *:60244 uid 6003": 365, "slurmd_req: received opcode REQUEST_ACCT_GATHER_UPDATE from *:60244 uid 6003": 366, "slurmd: slurmd_req: received opcode REQUEST_ACCT_GATHER_UPDATE from *:60376 uid 6003": 367, "slurmd_req: received opcode REQUEST_ACCT_GATHER_UPDATE from *:60376 uid 6003": 368, "slurmd: slurmd_req: received opcode REQUEST_PING from *:60490 uid 6003": 369, "slurmd_req: received opcode REQUEST_PING from *:60490 uid 6003": 370, "slurmd: slurmd_req: received opcode REQUEST_ACCT_GATHER_UPDATE from *:60616 uid 6003": 371, "slurmd_req: received opcode REQUEST_ACCT_GATHER_UPDATE from *:60616 uid 6003": 372, "slurmd: slurmd_req: received opcode REQUEST_HEALTH_CHECK from *:49320 uid 6003": 373, "slurmd_req: received opcode REQUEST_HEALTH_CHECK from *:49320 uid 6003": 374, "INFO [sshd] Found * - 2024-04-20 00:09:02": 375, "INFO [sshd] Found * - 2024-04-20 00:09:05": 376, "Startup finished in 72ms.": 377, "slurmd: slurmd_req: received opcode REQUEST_ACCT_GATHER_UPDATE from *:60774 uid 6003": 378, "slurmd_req: received opcode REQUEST_ACCT_GATHER_UPDATE from *:60774 uid 6003": 379, "Startup finished in 40ms.": 380, "slurmd: slurmd_req: received opcode REQUEST_ACCT_GATHER_UPDATE from *:60898 uid 6003": 381, "slurmd_req: received opcode REQUEST_ACCT_GATHER_UPDATE from *:60898 uid 6003": 382, "reverse mapping checking getaddrinfo for ip-193-186.bbn.net.id [*] failed.": 383, "Anacron started on *": 384, "*: from=*,size=**,nrcpt=** (*)": 385, "*: to=*, orig_to=*, *, *, **, *, status=status=*": 386, "Created slice user * of *.": 387, "Starting user * for *...": 388, "Starting D-Bus user * Bus Socket.": 389, "Listening on D-Bus user * Bus Socket.": 390, "Started user * for *.": 391, "Stopping user * for *...": 392, "Closed D-Bus user * Bus Socket.": 393, "Stopped user * for *.": 394, "Removed slice user * of *.": 395, "INFO [sshd] Found * - *": 396, "process * (*) of user * dumped core.": 397, "6BE563AD: from=*,size=**,nrcpt=** (*)": 398, "6BE563AD: to=*, orig_to=*, *, *, **, *, status=status=*": 399, "C718F19862: from=*,size=**,nrcpt=** (*)": 400, "C718F19862: to=*, orig_to=*, *, *, **, *, status=status=*": 401, "B18AF19862: from=*,size=**,nrcpt=** (*)": 402, "B18AF19862: to=*, orig_to=*, *, *, **, *, status=status=*": 403, "A0FFF2EAFE: from=*,size=**,nrcpt=** (*)": 404, "A0FFF2EAFE: to=*, orig_to=*, *, *, **, *, status=status=*": 405, "[13107679.batch] task 0 (*) started *T00:04:33": 406, "(*) STARTUP (*)": 407, "(*) INFO (*)": 408, "Will run job `cron.daily' in 5 min.": 409, "Will run job `cron.monthly' in 45 min.": 410, "Job `cron.monthly' started": 411, "Job `cron.monthly' terminated": 412, "(*) LIST (*)": 413, "  matteo : TTY=pts* ; PWD=* ; USER=root ; COMMAND=* restart rsyslog": 414, "pam_unix(*): session * for user *(*) by matteo(*)": 415, "  matteo : TTY=pts* ; PWD=* ; USER=root ; COMMAND=* *": 416, "  matteo : TTY=pts* ; PWD=* ; USER=root ; COMMAND=* secure_logs.log": 417, "gkr-pam: unlocked login keyring": 418, "  matteo : TTY=pts* ; PWD=* ; USER=root ; COMMAND=* allmessages.log": 419, "  matteo : TTY=pts* ; PWD=* ; USER=root ; COMMAND=* cron": 420, "pam_unix(*): session * for user *(*) by gdm(*)": 421, "pam_unix(*): session * for user *(*) by (*)": 422, "Registered Authentication Agent for unix-session:c1 (*)": 423, "Unregistered Authentication Agent for unix-session:c1 (*) (*)": 424, "Loading rules from directory *": 425, "Finished loading, compiling and executing 12 rules": 426, "Acquired the name org.freedesktop.PolicyKit1 on the system bus": 427, "failed adding user 'vboxadd', exit code: 9": 428, "Server listening on * port *.": 429, "Server listening on :: port *.": 430, "gkr-pam: unable to locate daemon control file": 431, "gkr-pam: stashed password to try later in open session": 432, "gkr-pam: gnome-keyring-daemon started properly and unlocked keyring": 433, "Registered Authentication Agent for unix-session:2 (*)": 434, "  matteo : TTY=pts* ; PWD=* ; USER=root ; COMMAND=* install audit": 435, "  matteo : TTY=pts* ; PWD=* ; USER=root ; COMMAND=* start auditd": 436, "  matteo : TTY=pts* ; PWD=* ; USER=root ; COMMAND=* enable auditd": 437, "  matteo : TTY=pts* ; PWD=* ; USER=root ; COMMAND=* -R *": 438, "  matteo : TTY=pts* ; PWD=* ; USER=root ; COMMAND=* cron_logs.log": 439, "  matteo : TTY=pts* ; PWD=* ; USER=root ; COMMAND=* -f laurel_logs": 440, "  matteo : TTY=pts* ; PWD=* ; USER=root ; COMMAND=* lastlog": 441, "  matteo : TTY=pts* ; PWD=* ; USER=root ; COMMAND=*": 442, "    root : TTY=pts* ; PWD=* ; USER=root ; COMMAND=* matteo": 443, "  matteo : TTY=pts* ; PWD=* ; USER=root ; COMMAND=* -f *": 444, "  matteo : TTY=pts* ; PWD=* ; USER=root ; COMMAND=* -l *": 445, "  matteo : TTY=pts* ; PWD=* ; USER=root ; COMMAND=* root:rsyslog *": 446, "  matteo : TTY=pts* ; PWD=* ; USER=root ; COMMAND=* 640 *": 447, "  matteo : TTY=pts* ; PWD=* ; USER=root ; COMMAND=* audit": 448, "    root : TTY=pts* ; PWD=* ; USER=root ; COMMAND=*": 449, "  matteo : TTY=pts* ; PWD=* ; USER=root ; COMMAND=* rsyslog.conf": 450, "  matteo : TTY=pts* ; PWD=* ; USER=root ; COMMAND=* 30-audit.conf": 451, "  matteo : TTY=pts* ; PWD=* ; USER=root ; COMMAND=* -f cron_logs.log": 452, "password check failed for user (*)": 453, "pam_unix(*): authentication failure; logname=matteo uid=0 euid=0 tty=* ruser= rhost=  user=matteo": 454, "gkr-pam: the password for the login keyring was invalid.": 455, "pam_unix(*): authentication failure; logname=matteo uid=1000 euid=0 tty=* ruser=matteo rhost=  user=matteo": 456, "pam_unix(*): authentication failure; logname=matteo uid=1000 euid=0 tty= ruser=matteo rhost=  user=matteo": 457, "pam_unix(*): authentication failure; logname=matteo uid=1000 euid=0 tty= ruser=matteo rhost=  user=root": 458, "  matteo : TTY=pts* ; PWD=* ; USER=root ; COMMAND=* -f secure_logs.log": 459, "  matteo : TTY=pts* ; PWD=* ; USER=root ; COMMAND=* -n 20 -f secure_logs.log": 460, "  matteo : TTY=pts* ; PWD=* ; USER=root ; COMMAND=* -n 50 -f secure_logs.log": 461, "  matteo : TTY=pts* ; PWD=* ; USER=root ; COMMAND=* -n 100 -f secure_logs.log": 462, "  matteo : TTY=pts* ; PWD=* ; USER=root ; COMMAND=* -n 10000 -f secure_logs.log": 463, "  matteo : TTY=pts* ; PWD=* ; USER=root ; COMMAND=* -n 1000 -f secure_logs.log": 464, "  matteo : TTY=pts* ; PWD=* ; USER=root ; COMMAND=* -n 1000 -f messages": 465, "  matteo : TTY=pts* ; PWD=* ; USER=root ; COMMAND=* -n 1000 messages": 466, "  matteo : TTY=pts* ; PWD=* ; USER=root ; COMMAND=* -n 1000 secure": 467, "  matteo : TTY=pts* ; PWD=* ; USER=root ; COMMAND=* -n 1000 cron": 468, "  matteo : TTY=pts* ; PWD=* ; USER=root ; COMMAND=* update": 469, "Reloading rules": 470, "Collecting garbage unconditionally...": 471, "  matteo : TTY=pts* ; PWD=* ; USER=root ; COMMAND=* install gcc kernel-dev kernel-headers dkms make bzip2 perl": 472, "  matteo : TTY=pts* ; PWD=* ; USER=root ; COMMAND=* install gcc kernel-devel kernel-headers dkms make bzip2 perl": 473, "  matteo : TTY=pts* ; PWD=* ; USER=root ; COMMAND=* install gcc kernel-devel kernel-headers make bzip2 perl": 474, "  matteo : TTY=pts* ; PWD=* ; USER=root ; COMMAND=* install epel-release": 475, "  matteo : TTY=pts* ; PWD=* ; USER=root ; COMMAND=* install dkms": 476, "  matteo : TTY=pts* ; PWD=* ; USER=root ; COMMAND=* * *": 477, "  matteo : TTY=pts* ; PWD=* ; USER=root ; COMMAND=* .*": 478, "  matteo : TTY=pts* ; PWD=* ; USER=root ; COMMAND=* status vboxadd": 479, "  matteo : TTY=pts* ; PWD=* ; USER=root ; COMMAND=* 0": 480, "  matteo : TTY=pts* ; PWD=* ; USER=root ; COMMAND=* cron_logs.log laurel_logs.log secure_logs.log user_logs.log */": 481, "REQUEST localhost - - \"POST / HTTP*\" 200 185 Renew-Subscription client-error-not-found": 482, "Could not release device (*): Cannot invoke method; proxy is for the well-known name org.freedesktop.login1 without an owner, and proxy was constructed with the G_DBUS_PROXY_FLAGS_DO_NOT_AUTO_START flag": 483, "GetManagedObjects(*) failed: org.freedesktop.DBus.Error.NameHasNoOwner": 484, "Could not open device *: GDBus.Error:org.freedesktop.login1.DeviceIsTaken: Device already taken": 485, "unable to get EDID for xrandr-Virtual-1: unable to get EDID for output": 486, "Unable to get default source": 487, "Unable to get default sink": 488, "Ready": 489, "Adding device '*' (*) using non-atomic mode setting (*).": 490, "VMware: No 3D enabled (*).": 491, "Failed to initialize accelerated iGPU* framebuffer sharing: Do not want to use software renderer (*)), falling back to CPU copy path": 492, "libEGL warning: egl: failed to create dri2 screen": 493, "Created gbm renderer for '*'": 494, "Boot VGA GPU * selected as primary": 495, "Disabling DMA buffer screen sharing for driver 'vmwgfx'.": 496, "Using public X11 display :1024, (*)": 497, "Using Wayland display name 'wayland-0'": 498, "dbus-daemon[3941]: [session *=42 pid=3941] Activating service name='org.a11y.Bus' requested by ':1.10' (*)": 499, "dbus-daemon[3941]: [session *=42 pid=3941] Successfully activated service 'org.a11y.Bus'": 500, "Skipping parental controls support as it\u2019s disabled": 501, "Unset XDG_SESSION_ID, getCurrentSessionProxy(*) called outside a user *. Asking logind directly.": 502, "Will monitor session *": 503, "dbus-daemon[3941]: [session *=42 pid=3941] Activating service name='org.freedesktop.impl.portal.PermissionStore' requested by ':1.9' (*)": 504, "dbus-daemon[3941]: [session *=42 pid=3941] Activating service name='org.freedesktop.portal.IBus' requested by ':1.12' (*)": 505, "dbus-daemon[3941]: [session *=42 pid=3941] Successfully activated service 'org.freedesktop.impl.portal.PermissionStore'": 506, "dbus-daemon[3941]: [session *=42 pid=3941] Successfully activated service 'org.freedesktop.portal.IBus'": 507, "SPA handle 'api.libcamera.enum.manager' could not be loaded; is it installed?": 508, "PipeWire's libcamera SPA missing or broken. libcamera not supported.": 509, "The decibel volume range for element 'Center' (*) has negative maximum. Disabling the decibel range.": 510, "The decibel volume range for element 'LFE' (*) has negative maximum. Disabling the decibel range.": 511, "dbus-daemon[3941]: [session *=42 pid=3941] Activating service name='org.gnome.Shell.Notifications' requested by ':1.9' (*)": 512, "dbus-daemon[4006]: Activating service name='org.a11y.atspi.Registry' requested by ':1.0' (*)": 513, "dbus-daemon[4006]: Successfully activated service 'org.a11y.atspi.Registry'": 514, "SpiRegistry daemon is running with well-known name - org.a11y.atspi.Registry": 515, "dbus-daemon[3941]: [session *=42 pid=3941] Successfully activated service 'org.gnome.Shell.Notifications'": 516, "dbus-daemon[3941]: [session *=42 pid=3941] Activating service name='org.freedesktop.systemd1' requested by ':1.18' (*)": 517, "dbus-daemon[3941]: [session *=42 pid=3941] Activated service 'org.freedesktop.systemd1' failed: Process org.freedesktop.systemd1 exited with status 1": 518, "Failed to StopUnit service: GDBus.Error:org.freedesktop.DBus.Error.Spawn.ChildExited: Process org.freedesktop.systemd1 exited with status 1": 519, "REQUEST localhost - - \"POST / HTTP*\" 200 359 Create-Printer-Subscriptions successful-ok": 520, "Error looking up permission: GDBus.Error:org.freedesktop.portal.Error.NotFound: No entry for geolocation": 521, "Failed to initialize glamor, falling back to sw": 522, "dbus-daemon[3941]: [session *=42 pid=3941] Activating service name='org.gnome.Shell.Screencast' requested by ':1.31' (*)": 523, "vdagent virtio channel * does not exist, exiting": 524, "Entering running state": 525, "dbus-daemon[3941]: [session *=42 pid=3941] Activating service name='org.gnome.ScreenSaver' requested by ':1.30' (*)": 526, "ATK Bridge is disabled but a11y has already been enabled.": 527, "dbus-daemon[3941]: [session *=42 pid=3941] Activating service name='org.freedesktop.portal.IBus' requested by ':1.40' (*)": 528, "dbus-daemon[3941]: [session *=42 pid=3941] Successfully activated service 'org.gnome.ScreenSaver'": 529, "failed to get edid: unable to get EDID for output": 530, "Failed to grab accelerator for keybinding settings:hibernate": 531, "Failed to grab accelerator for keybinding settings:playback-repeat": 532, "The XKEYBOARD keymap compiler (*) reports:": 533, "> Warning:          Unsupported maximum keycode 708, clipping.": 534, ">                   X11 cannot support keycodes above 255.": 535, "Errors from xkbcomp are not fatal to the X server": 536, "dbus-daemon[3941]: [session *=42 pid=3941] Successfully activated service 'org.gnome.Shell.Screencast'": 537, "Registering session * GDM": 538, "Service not used for 60 seconds. Shutting down..": 539, "REQUEST localhost - - \"POST / HTTP*\" 200 182 Renew-Subscription client-error-not-found": 540, "gvc_mixer_card_get_index: assertion 'GVC_IS_MIXER_CARD (*)' failed": 541, "Connection to xwayland lost": 542, "gnome-session *[3942]: WARNING: Lost name on bus: org.gnome.SessionManager": 543, "REQUEST localhost - - \"POST / HTTP*\" 200 151 Cancel-Subscription client-error-not-found": 544, "Error releasing name org.gnome.SettingsDaemon.Sharing: The connection is closed": 545, "GLib: Source ID 2 was not found when attempting to remove it": 546, "Error releasing name org.gnome.SettingsDaemon.Rfkill: The connection is closed": 547, "Error releasing name org.gnome.SettingsDaemon.Smartcard: The connection is closed": 548, "Error releasing name org.gnome.SettingsDaemon.Sound: The connection is closed": 549, "Error releasing name org.gnome.SettingsDaemon.Housekeeping: The connection is closed": 550, "Error releasing name org.freedesktop.ScreenSaver: The connection is closed": 551, "GLib-GObject: g_object_unref: assertion 'G_IS_OBJECT (*)' failed": 552, "Gdm: Child process -3930 was already dead.": 553, "stopped by signal: Terminated": 554, "disconnected from pipewire": 555, "PV * online, VG rl is complete.": 556, "udisks daemon version 2.9.4 starting": 557, "Acquired the name org.freedesktop.UDisks2 on the system message bus": 558, "Starting VirtualBox Guest Addition service.": 559, "dbus-daemon[1962]: [session *=42 pid=1962] Activating service name='org.a11y.Bus' requested by ':1.2' (*)": 560, "dbus-daemon[1962]: [session *=42 pid=1962] Successfully activated service 'org.a11y.Bus'": 561, "dbus-daemon[1962]: [session *=42 pid=1962] Activating service name='org.freedesktop.portal.IBus' requested by ':1.4' (*)": 562, "dbus-daemon[1962]: [session *=42 pid=1962] Activating service name='org.freedesktop.impl.portal.PermissionStore' requested by ':1.1' (*)": 563, "dbus-daemon[1962]: [session *=42 pid=1962] Successfully activated service 'org.freedesktop.portal.IBus'": 564, "dbus-daemon[1962]: [session *=42 pid=1962] Successfully activated service 'org.freedesktop.impl.portal.PermissionStore'": 565, "dbus-daemon[1962]: [session *=42 pid=1962] Activating service name='org.gnome.Shell.Notifications' requested by ':1.1' (*)": 566, "dbus-daemon[1991]: Activating service name='org.a11y.atspi.Registry' requested by ':1.0' (*)": 567, "dbus-daemon[1991]: Successfully activated service 'org.a11y.atspi.Registry'": 568, "dbus-daemon[1962]: [session *=42 pid=1962] Successfully activated service 'org.gnome.Shell.Notifications'": 569, "dbus-daemon[1962]: [session *=42 pid=1962] Activating service name='org.freedesktop.systemd1' requested by ':1.11' (*)": 570, "dbus-daemon[1962]: [session *=42 pid=1962] Activated service 'org.freedesktop.systemd1' failed: Process org.freedesktop.systemd1 exited with status 1": 571, "dbus-daemon[1962]: [session *=42 pid=1962] Activating service name='org.gnome.Shell.Screencast' requested by ':1.23' (*)": 572, "failed to get edid data: EDID length is too small": 573, "dbus-daemon[1962]: [session *=42 pid=1962] Activating service name='org.gnome.ScreenSaver' requested by ':1.24' (*)": 574, "dbus-daemon[1962]: [session *=42 pid=1962] Activating service name='org.freedesktop.portal.IBus' requested by ':1.31' (*)": 575, "dbus-daemon[1962]: [session *=42 pid=1962] Successfully activated service 'org.gnome.ScreenSaver'": 576, "dbus-daemon[1962]: [session *=42 pid=1962] Successfully activated service 'org.gnome.Shell.Screencast'": 577, "SSH_AUTH_SOCK=*": 578, "gnome-session *[2452]: GnomeDesktop-WARNING: Could not create transient scope for PID 2466: GDBus.Error:org.freedesktop.DBus.Error.UnixProcessIdUnknown: Process with ID 2466 does not exist.": 579, "Using public X11 display :0, (*)": 580, "g_strsplit: assertion 'string != NULL' failed": 581, "goa-daemon version 3.40.0 starting": 582, "Telepathy is not available, chat integration will be disabled.": 583, "GoaKerberosIdentityManager: Using polling for change notification for credential cache type 'KCM'": 584, "Unable to connect to ibus: Could not connect: Connection refused": 585, "vmware-user: could not open *": 586, "Mounted * at * on behalf of uid 1000": 587, "gnome-session *[2452]: GnomeDesktop-WARNING: Could not create transient scope for PID 2687: GDBus.Error:org.freedesktop.DBus.Error.UnixProcessIdUnknown: Process with ID 2687 does not exist.": 588, "gnome-session *[2452]: GnomeDesktop-WARNING: Could not create transient scope for PID 2723: GDBus.Error:org.freedesktop.DBus.Error.UnixProcessIdUnknown: Process with ID 2723 does not exist.": 589, "REQUEST localhost - - \"POST / HTTP*\" 200 362 Create-Printer-Subscriptions successful-ok": 590, "gnome-session *[2452]: GnomeDesktop-WARNING: Could not create transient scope for PID 2727: GDBus.Error:org.freedesktop.DBus.Error.UnixProcessIdUnknown: Process with ID 2727 does not exist.": 591, "Failed to fetch USBGuard parameters: GDBus.Error:org.freedesktop.DBus.Error.ServiceUnknown: The name is not activatable": 592, "enabled plugins: appstream, fwupd, os-release, packagekit-refresh, flatpak, hardcoded-blocklist, hardcoded-popular, modalias, packagekit, rewrite-resource, provenance, repos, systemd-updates, generic-updates, packagekit-refine-repos, provenance-license, icons": 593, "disabled plugins: dummy, fedora-langpacks, fedora-pkgdb-collections": 594, "GNOME Shell started at Sun Jun 23 2024 05:30:08 GMT-0400 (*)": 595, "Gdm: Child process -1956 was already dead.": 596, "Only 0 apps for recent list, hiding": 597, "Only 1 apps for popular list, hiding": 598, "Failed to get cache filename for firefox": 599, "Failed to get cache filename for cockpit-storaged": 600, "Failed to get cache filename for cockpit": 601, "Failed to get cache filename for gnome-screenshot": 602, "Failed to get cache filename for python3-idna": 603, "Failed to get cache filename for selinux-policy-targeted": 604, "Failed to get cache filename for selinux-policy": 605, "Failed to get cache filename for c-ares": 606, "Failed to get cache filename for xfsdump": 607, "Failed to get cache filename for libnghttp2": 608, "Failed to get cache filename for less": 609, "Failed to get cache filename for samba-common-libs": 610, "Failed to get cache filename for samba-common": 611, "Failed to get cache filename for samba-client-libs": 612, "Failed to get cache filename for libwbclient": 613, "Failed to get cache filename for libsmbclient": 614, "Failed to get cache filename for cockpit-ws": 615, "Failed to get cache filename for cockpit-bridge": 616, "Failed to get cache filename for cockpit-system": 617, "Failed to get cache filename for NetworkManager-config-server": 618, "Failed to get cache filename for glibc-langpack-en": 619, "Failed to get cache filename for glibc-gconv-extra": 620, "Failed to get cache filename for glibc-common": 621, "Failed to get cache filename for glibc-all-langpacks": 622, "Failed to get cache filename for glibc": 623, "Failed to get cache filename for NetworkManager-wwan": 624, "Failed to get cache filename for NetworkManager-wifi": 625, "Failed to get cache filename for NetworkManager-tui": 626, "Failed to get cache filename for NetworkManager-team": 627, "Failed to get cache filename for NetworkManager-libnm": 628, "Failed to get cache filename for NetworkManager-bluetooth": 629, "Failed to get cache filename for NetworkManager-adsl": 630, "Failed to get cache filename for NetworkManager": 631, "Failed to get cache filename for rocky-repos": 632, "Failed to get cache filename for rocky-release": 633, "Failed to get cache filename for rocky-gpg-keys": 634, "Failed to get cache filename for grub2-tools-minimal": 635, "Failed to get cache filename for grub2-tools": 636, "Failed to get cache filename for grub2-pc": 637, "Failed to get cache filename for grub2-pc-modules": 638, "Failed to get cache filename for grub2-common": 639, "Failed to get cache filename for python3-perf": 640, "Failed to get cache filename for kernel-tools-libs": 641, "Failed to get cache filename for kernel-tools": 642, "Failed to get cache filename for bpftool": 643, "Failed to get cache filename for containernetworking-plugins": 644, "Failed to get cache filename for flatpak-session *": 645, "Failed to get cache filename for flatpak-libs": 646, "Failed to get cache filename for flatpak": 647, "Failed to get cache filename for flatpak-selinux": 648, "Failed to get cache filename for buildah": 649, "Failed to get cache filename for podman": 650, "Failed to get cache filename for cockpit-packagekit": 651, "Failed to get cache filename for libgs": 652, "Failed to get cache filename for ghostscript-tools-printing": 653, "Failed to get cache filename for ghostscript-tools-fonts": 654, "Failed to get cache filename for ghostscript": 655, "Failed to get cache filename for pixman": 656, "Failed to get cache filename for ostree-libs": 657, "Failed to get cache filename for ostree": 658, "Failed to get cache filename for qemu-guest-agent": 659, "Failed to get cache filename for libappstream-glib": 660, "Failed to get cache filename for gdk-pixbuf2-modules": 661, "Failed to get cache filename for gdk-pixbuf2": 662, "Failed to get cache filename for grub2-tools-extra": 663, "Failed to get cache filename for grub2-tools-efi": 664, "Failed to get cache filename for kernel-modules-core": 665, "Failed to get cache filename for kernel-modules": 666, "Failed to get cache filename for kernel-core": 667, "Failed to get cache filename for kernel": 668, "Failed to get cache filename for composefs-libs": 669, "Failed to get cache filename for composefs": 670, "SELinux is preventing * from search access on the directory *. For complete SELinux messages run: sealert -l 7c66cbcf-11a9-4295-a7be-90af9b3df2dc": 671, "SELinux is preventing * from search access on the directory ******  Plugin catchall (*) suggests   **************************#012#012If you believe that rsyslogd should be allowed search access on the audit.log directory by default.#012Then you should report this as a bug.#012You can generate a local policy module to allow this access.#012Do#012allow this access for now by executing:#012# ausearch -c 'rsyslogd' --raw | audit2allow -M my-rsyslogd#012# semodule -X 300 -i my-rsyslogd.pp#012": 672, "SELinux is preventing * from getattr access on the directory *. For complete SELinux messages run: sealert -l c9fe4dec-b9bd-4c50-92cc-ca9bd14d4034": 673, "SELinux is preventing * from getattr access on the directory ******  Plugin catchall (*) suggests   **************************#012#012If you believe that rsyslogd should be allowed getattr access on the audit directory by default.#012Then you should report this as a bug.#012You can generate a local policy module to allow this access.#012Do#012allow this access for now by executing:#012# ausearch -c 'in:imfile' --raw | audit2allow -M my-inimfile#012# semodule -X 300 -i my-inimfile.pp#012": 674, "dbus-daemon[1960]: [session *=42 pid=1960] Activating service name='org.a11y.Bus' requested by ':1.4' (*)": 675, "dbus-daemon[1960]: [session *=42 pid=1960] Successfully activated service 'org.a11y.Bus'": 676, "dbus-daemon[1960]: [session *=42 pid=1960] Activating service name='org.freedesktop.portal.IBus' requested by ':1.6' (*)": 677, "dbus-daemon[1960]: [session *=42 pid=1960] Successfully activated service 'org.freedesktop.portal.IBus'": 678, "dbus-daemon[1960]: [session *=42 pid=1960] Activating service name='org.freedesktop.impl.portal.PermissionStore' requested by ':1.3' (*)": 679, "dbus-daemon[1960]: [session *=42 pid=1960] Successfully activated service 'org.freedesktop.impl.portal.PermissionStore'": 680, "<WpNode:0x556b1a6002f0> ignoring set_param on already destroyed objects": 681, "<WpNode:0x556b1a6001f0> ignoring set_param on already destroyed objects": 682, "dbus-daemon[1960]: [session *=42 pid=1960] Activating service name='org.gnome.Shell.Notifications' requested by ':1.3' (*)": 683, "dbus-daemon[1989]: Activating service name='org.a11y.atspi.Registry' requested by ':1.0' (*)": 684, "dbus-daemon[1989]: Successfully activated service 'org.a11y.atspi.Registry'": 685, "dbus-daemon[1960]: [session *=42 pid=1960] Successfully activated service 'org.gnome.Shell.Notifications'": 686, "dbus-daemon[1960]: [session *=42 pid=1960] Activating service name='org.freedesktop.systemd1' requested by ':1.13' (*)": 687, "dbus-daemon[1960]: [session *=42 pid=1960] Activated service 'org.freedesktop.systemd1' failed: Process org.freedesktop.systemd1 exited with status 1": 688, "dbus-daemon[1960]: [session *=42 pid=1960] Activating service name='org.gnome.Shell.Screencast' requested by ':1.24' (*)": 689, "dbus-daemon[1960]: [session *=42 pid=1960] Activating service name='org.gnome.ScreenSaver' requested by ':1.26' (*)": 690, "dbus-daemon[1960]: [session *=42 pid=1960] Activating service name='org.freedesktop.portal.IBus' requested by ':1.33' (*)": 691, "dbus-daemon[1960]: [session *=42 pid=1960] Successfully activated service 'org.gnome.ScreenSaver'": 692, "dbus-daemon[1960]: [session *=42 pid=1960] Successfully activated service 'org.gnome.Shell.Screencast'": 693, "<WpNode:0x561228f64e80> ignoring set_param on already destroyed objects": 694, "<WpNode:0x561228f64d80> ignoring set_param on already destroyed objects": 695, "<WpSiAudioAdapter:0x56122918d060> Object activation aborted: proxy destroyed": 696, "<WpSiAudioAdapter:0x56122918d060> failed to activate item: Object activation aborted: proxy destroyed": 697, "gnome-session *[2437]: GnomeDesktop-WARNING: Could not create transient scope for PID 2660: GDBus.Error:org.freedesktop.DBus.Error.UnixProcessIdUnknown: Process with ID 2660 does not exist.": 698, "gnome-session *[2437]: GnomeDesktop-WARNING: Could not create transient scope for PID 2675: GDBus.Error:org.freedesktop.DBus.Error.UnixProcessIdUnknown: Process with ID 2675 does not exist.": 699, "gnome-session *[2437]: GnomeDesktop-WARNING: Could not create transient scope for PID 2676: GDBus.Error:org.freedesktop.DBus.Error.UnixProcessIdUnknown: Process with ID 2676 does not exist.": 700, "gnome-session *[2437]: GnomeDesktop-WARNING: Could not create transient scope for PID 2706: GDBus.Error:org.freedesktop.DBus.Error.UnixProcessIdUnknown: Process with ID 2706 does not exist.": 701, "GNOME Shell started at Sun Jun 23 2024 05:50:35 GMT-0400 (*)": 702, "REQUEST localhost - - \"POST / HTTP*\" 200 151 Cancel-Subscription successful-ok": 703, "Error releasing name org.gnome.SettingsDaemon.PrintNotifications: The connection is closed": 704, "Error releasing name org.gnome.SettingsDaemon.A11ySettings: The connection is closed": 705, "Lost or failed to acquire name org.gnome.Mutter.ScreenCast": 706, "Lost or failed to acquire name org.gnome.Mutter.RemoteDesktop": 707, "gnome-session *[1961]: WARNING: Lost name on bus: org.gnome.SessionManager": 708, "REQUEST localhost - - \"POST / HTTP*\" 200 185 Renew-Subscription successful-ok": 709, "SELinux is preventing * from read access on the file *. For complete SELinux messages run: sealert -l 9626d584-1ef3-449a-a4ab-c94124f64237": 710, "SELinux is preventing * from read access on the file ******  Plugin catchall (*) suggests   **************************#012#012If you believe that rsyslogd should be allowed read access on the audit.log file by default.#012Then you should report this as a bug.#012You can generate a local policy module to allow this access.#012Do#012allow this access for now by executing:#012# ausearch -c 'rsyslogd' --raw | audit2allow -M my-rsyslogd#012# semodule -X 300 -i my-rsyslogd.pp#012": 711, "SELinux is preventing * from read access on the directory *. For complete SELinux messages run: sealert -l 92180865-4a86-4e35-b9d7-35e5c68fcdff": 712, "SELinux is preventing * from read access on the directory ******  Plugin catchall (*) suggests   **************************#012#012If you believe that rsyslogd should be allowed read access on the audit directory by default.#012Then you should report this as a bug.#012You can generate a local policy module to allow this access.#012Do#012allow this access for now by executing:#012# ausearch -c 'in:imfile' --raw | audit2allow -M my-inimfile#012# semodule -X 300 -i my-inimfile.pp#012": 713, "SELinux is preventing * from open access on the directory *. For complete SELinux messages run: sealert -l 038dcf07-3c25-4d31-a162-86e5b195bee2": 714, "SELinux is preventing * from open access on the directory ******  Plugin catchall (*) suggests   **************************#012#012If you believe that rsyslogd should be allowed open access on the audit directory by default.#012Then you should report this as a bug.#012You can generate a local policy module to allow this access.#012Do#012allow this access for now by executing:#012# ausearch -c 'in:imfile' --raw | audit2allow -M my-inimfile#012# semodule -X 300 -i my-inimfile.pp#012": 715, "SELinux is preventing * from watch access on the directory *. For complete SELinux messages run: sealert -l 6df232d9-ae22-4762-98ed-2774df3b9be0": 716, "SELinux is preventing * from watch access on the directory ******  Plugin catchall (*) suggests   **************************#012#012If you believe that rsyslogd should be allowed watch access on the audit directory by default.#012Then you should report this as a bug.#012You can generate a local policy module to allow this access.#012Do#012allow this access for now by executing:#012# ausearch -c 'in:imfile' --raw | audit2allow -M my-inimfile#012# semodule -X 300 -i my-inimfile.pp#012": 717, "SELinux is preventing * from getattr access on the file *. For complete SELinux messages run: sealert -l ede0e9c1-c0db-4356-86ba-b7560852a967": 718, "SELinux is preventing * from getattr access on the file ******  Plugin catchall (*) suggests   **************************#012#012If you believe that rsyslogd should be allowed getattr access on the audit.log file by default.#012Then you should report this as a bug.#012You can generate a local policy module to allow this access.#012Do#012allow this access for now by executing:#012# ausearch -c 'in:imfile' --raw | audit2allow -M my-inimfile#012# semodule -X 300 -i my-inimfile.pp#012": 719, "SELinux is preventing * from open access on the file *. For complete SELinux messages run: sealert -l 327cef9a-0064-483e-81bc-0189915e0d6a": 720, "SELinux is preventing * from open access on the file ******  Plugin catchall (*) suggests   **************************#012#012If you believe that rsyslogd should be allowed open access on the audit.log file by default.#012Then you should report this as a bug.#012You can generate a local policy module to allow this access.#012Do#012allow this access for now by executing:#012# ausearch -c 'in:imfile' --raw | audit2allow -M my-inimfile#012# semodule -X 300 -i my-inimfile.pp#012": 721, "SELinux is preventing * from watch access on the file *. For complete SELinux messages run: sealert -l a6273aff-5a7c-43d3-977a-c3440d28dcc0": 722, "SELinux is preventing * from watch access on the file ******  Plugin catchall (*) suggests   **************************#012#012If you believe that rsyslogd should be allowed watch access on the audit.log file by default.#012Then you should report this as a bug.#012You can generate a local policy module to allow this access.#012Do#012allow this access for now by executing:#012# ausearch -c 'in:imfile' --raw | audit2allow -M my-inimfile#012# semodule -X 300 -i my-inimfile.pp#012": 723, "SELinux is preventing * from ioctl access on the file *. For complete SELinux messages run: sealert -l e0def7f7-b7fa-426f-b067-4ccf6db60347": 724, "SELinux is preventing * from ioctl access on the file ******  Plugin catchall (*) suggests   **************************#012#012If you believe that rsyslogd should be allowed ioctl access on the audit.log file by default.#012Then you should report this as a bug.#012You can generate a local policy module to allow this access.#012Do#012allow this access for now by executing:#012# ausearch -c 'in:imfile' --raw | audit2allow -M my-inimfile#012# semodule -X 300 -i my-inimfile.pp#012": 725, "Deleting alert 9626d584-1ef3-449a-a4ab-c94124f64237, it is allowed in current policy": 726, "Deleting alert 7c66cbcf-11a9-4295-a7be-90af9b3df2dc, it is allowed in current policy": 727, "dbus-daemon[1959]: [session *=42 pid=1959] Activating service name='org.a11y.Bus' requested by ':1.4' (*)": 728, "dbus-daemon[1959]: [session *=42 pid=1959] Successfully activated service 'org.a11y.Bus'": 729, "dbus-daemon[1959]: [session *=42 pid=1959] Activating service name='org.freedesktop.impl.portal.PermissionStore' requested by ':1.3' (*)": 730, "dbus-daemon[1959]: [session *=42 pid=1959] Activating service name='org.freedesktop.portal.IBus' requested by ':1.6' (*)": 731, "dbus-daemon[1959]: [session *=42 pid=1959] Successfully activated service 'org.freedesktop.impl.portal.PermissionStore'": 732, "dbus-daemon[1959]: [session *=42 pid=1959] Successfully activated service 'org.freedesktop.portal.IBus'": 733, "<WpNode:0x562eb6d65e80> ignoring set_param on already destroyed objects": 734, "<WpNode:0x562eb6d65d80> ignoring set_param on already destroyed objects": 735, "<WpSiAudioAdapter:0x562eb6f83070> Object activation aborted: proxy destroyed": 736, "<WpSiAudioAdapter:0x562eb6f83070> failed to activate item: Object activation aborted: proxy destroyed": 737, "dbus-daemon[1959]: [session *=42 pid=1959] Activating service name='org.gnome.Shell.Notifications' requested by ':1.3' (*)": 738, "dbus-daemon[1987]: Activating service name='org.a11y.atspi.Registry' requested by ':1.0' (*)": 739, "dbus-daemon[1987]: Successfully activated service 'org.a11y.atspi.Registry'": 740, "dbus-daemon[1959]: [session *=42 pid=1959] Activating service name='org.freedesktop.systemd1' requested by ':1.12' (*)": 741, "dbus-daemon[1959]: [session *=42 pid=1959] Activated service 'org.freedesktop.systemd1' failed: Process org.freedesktop.systemd1 exited with status 1": 742, "dbus-daemon[1959]: [session *=42 pid=1959] Successfully activated service 'org.gnome.Shell.Notifications'": 743, "dbus-daemon[1959]: [session *=42 pid=1959] Activating service name='org.gnome.Shell.Screencast' requested by ':1.25' (*)": 744, "dbus-daemon[1959]: [session *=42 pid=1959] Activating service name='org.freedesktop.portal.IBus' requested by ':1.33' (*)": 745, "dbus-daemon[1959]: [session *=42 pid=1959] Activating service name='org.gnome.ScreenSaver' requested by ':1.26' (*)": 746, "dbus-daemon[1959]: [session *=42 pid=1959] Successfully activated service 'org.gnome.Shell.Screencast'": 747, "dbus-daemon[1959]: [session *=42 pid=1959] Successfully activated service 'org.gnome.ScreenSaver'": 748, "<WpSiAudioAdapter:0x560f4474f060> Object activation aborted: proxy destroyed": 749, "<WpSiAudioAdapter:0x560f4474f060> failed to activate item: Object activation aborted: proxy destroyed": 750, "gnome-session *[2456]: GnomeDesktop-WARNING: Could not create transient scope for PID 2688: GDBus.Error:org.freedesktop.DBus.Error.UnixProcessIdUnknown: Process with ID 2688 does not exist.": 751, "gnome-session *[2456]: GnomeDesktop-WARNING: Could not create transient scope for PID 2747: GDBus.Error:org.freedesktop.DBus.Error.UnixProcessIdUnknown: Process with ID 2747 does not exist.": 752, "plugin flatpak took 1.6 seconds to do initialize": 753, "GNOME Shell started at Mon Jun 24 2024 10:45:12 GMT-0400 (*)": 754, "plugin fwupd took 3.1 seconds to do setup": 755, "failed to get featured apps: no apps to show": 756, "Failed to get cache filename for sos": 757, "Failed to create proxy for screencast: Error calling StartServiceByName for org.gnome.Shell.Screencast: Timeout was reached": 758, "*.600547753 -0400 EDT m=+0.263459699 system refresh": 759, "[Client 7] Request from \"localhost\" using invalid Host: field \"linpeas\".": 760, "sim_lsmplugin: Traceback (*):": 761, "sim_lsmplugin:   File \"*\", line 98, in run": 762, "sim_lsmplugin:     msg = self.tp.read_req(*)": 763, "sim_lsmplugin:   File \"*\", line 149, in read_req": 764, "sim_lsmplugin:     data = self._recv_msg(*)": 765, "sim_lsmplugin:   File \"*\", line 84, in _recv_msg": 766, "sim_lsmplugin:     msg = self._read_all(*))": 767, "sim_lsmplugin: ValueError: invalid literal for int(*) with base 10: 'GET / HTTP'": 768, "sim_lsmplugin: ValueError: invalid literal for int(*) with base 10: '*'": 769, "sim_lsmplugin: Client went away, exiting plug-in": 770, "Plug-in exception: Unreachable path!": 771, "pw.resource: client error -71 (*)": 772, "mod.protocol-native: 0x55697daf7050: connection_data: client 0x55697dcb0130 error -71 (*)": 773, "mod.protocol-native: 0x55697daf7050: connection_data: client 0x55697dcce060 error -71 (*)": 774, "sim_lsmplugin: ValueError: invalid literal for int(*) with base 10: ': linpeas\\r'": 775, "sim_lsmplugin: ValueError: invalid literal for int(*) with base 10: '\\nUser-Agen'": 776, "sim_lsmplugin: ValueError: invalid literal for int(*) with base 10: 't: curl*.'": 777, "sim_lsmplugin: ValueError: invalid literal for int(*) with base 10: '76.1\\r\\nAcce'": 778, "sim_lsmplugin: ValueError: invalid literal for int(*) with base 10: 'pt: **'": 779, "[Client 9] Request from \"localhost\" using invalid Host: field \"linpeas\".": 780, "mod.protocol-native: 0x55697daf7050: connection_data: client 0x55697dcb29a0 error -71 (*)": 781, "mod.protocol-native: 0x55697daf7050: connection_data: client 0x55697dcd2d50 error -71 (*)": 782, "[Client 11] Request from \"localhost\" using invalid Host: field \"linpeas\".": 783, "mod.protocol-native: 0x55697daf7050: connection_data: client 0x55697dcccd80 error -71 (*)": 784, "mod.protocol-native: 0x55697daf7050: connection_data: client 0x55697dcda010 error -71 (*)": 785, "dbus-daemon[2143]: [session *=42 pid=2143] Activating service name='org.a11y.Bus' requested by ':1.4' (*)": 786, "dbus-daemon[2143]: [session *=42 pid=2143] Successfully activated service 'org.a11y.Bus'": 787, "dbus-daemon[2143]: [session *=42 pid=2143] Activating service name='org.freedesktop.impl.portal.PermissionStore' requested by ':1.3' (*)": 788, "dbus-daemon[2143]: [session *=42 pid=2143] Activating service name='org.freedesktop.portal.IBus' requested by ':1.6' (*)": 789, "dbus-daemon[2143]: [session *=42 pid=2143] Successfully activated service 'org.freedesktop.impl.portal.PermissionStore'": 790, "dbus-daemon[2143]: [session *=42 pid=2143] Successfully activated service 'org.freedesktop.portal.IBus'": 791, "dbus-daemon[2143]: [session *=42 pid=2143] Activating service name='org.gnome.Shell.Notifications' requested by ':1.3' (*)": 792, "dbus-daemon[2171]: Activating service name='org.a11y.atspi.Registry' requested by ':1.0' (*)": 793, "dbus-daemon[2171]: Successfully activated service 'org.a11y.atspi.Registry'": 794, "dbus-daemon[2143]: [session *=42 pid=2143] Activating service name='org.freedesktop.systemd1' requested by ':1.12' (*)": 795, "dbus-daemon[2143]: [session *=42 pid=2143] Successfully activated service 'org.gnome.Shell.Notifications'": 796, "dbus-daemon[2143]: [session *=42 pid=2143] Activated service 'org.freedesktop.systemd1' failed: Process org.freedesktop.systemd1 exited with status 1": 797, "dbus-daemon[2143]: [session *=42 pid=2143] Activating service name='org.freedesktop.portal.IBus' requested by ':1.33' (*)": 798, "dbus-daemon[2143]: [session *=42 pid=2143] Activating service name='org.gnome.Shell.Screencast' requested by ':1.23' (*)": 799, "dbus-daemon[2143]: [session *=42 pid=2143] Activating service name='org.gnome.ScreenSaver' requested by ':1.25' (*)": 800, "dbus-daemon[2143]: [session *=42 pid=2143] Successfully activated service 'org.gnome.ScreenSaver'": 801, "dbus-daemon[2143]: [session *=42 pid=2143] Successfully activated service 'org.gnome.Shell.Screencast'": 802, "<WpSiAudioAdapter:0x557c4b545050> Object activation aborted: proxy destroyed": 803, "<WpSiAudioAdapter:0x557c4b545050> failed to activate item: Object activation aborted: proxy destroyed": 804, "gnome-session *[2634]: GnomeDesktop-WARNING: Could not create transient scope for PID 2861: GDBus.Error:org.freedesktop.DBus.Error.UnixProcessIdUnknown: Process with ID 2861 does not exist.": 805, "gnome-session *[2634]: GnomeDesktop-WARNING: Could not create transient scope for PID 2876: GDBus.Error:org.freedesktop.DBus.Error.UnixProcessIdUnknown: Process with ID 2876 does not exist.": 806, "gnome-session *[2634]: GnomeDesktop-WARNING: Could not create transient scope for PID 2884: GDBus.Error:org.freedesktop.DBus.Error.UnixProcessIdUnknown: Process with ID 2884 does not exist.": 807, "GNOME Shell started at Tue Jun 25 2024 04:30:04 GMT-0400 (*)": 808, "plugin flatpak took 3.3 seconds to do initialize": 809, "dracut-057-53.git20240104.el9": 810, "Executing: * -f * 5.14.0-427.22.1.el9_4.x86_64": 811, "dracut module 'systemd-networkd' will not be installed, because command 'networkctl' could not be found!": 812, "dracut module 'systemd-networkd' will not be installed, because command '*' could not be found!": 813, "dracut module 'systemd-resolved' will not be installed, because command 'resolvectl' could not be found!": 814, "dracut module 'systemd-resolved' will not be installed, because command '*' could not be found!": 815, "dracut module 'systemd-timesyncd' will not be installed, because command '*' could not be found!": 816, "dracut module 'modsign' will not be installed, because command 'keyctl' could not be found!": 817, "dracut module 'busybox' will not be installed, because command 'busybox' could not be found!": 818, "dracut module 'rngd' will not be installed, because command 'rngd' could not be found!": 819, "dracut module 'connman' will not be installed, because command 'connmand' could not be found!": 820, "dracut module 'connman' will not be installed, because command 'connmanctl' could not be found!": 821, "dracut module 'connman' will not be installed, because command 'connmand-wait-online' could not be found!": 822, "dracut module 'network-legacy' will not be installed, because command 'dhclient' could not be found!": 823, "dracut module 'network-wicked' will not be installed, because command 'wicked' could not be found!": 824, "dracut module 'btrfs' will not be installed, because command 'btrfs' could not be found!": 825, "dracut module 'dmraid' will not be installed, because command 'dmraid' could not be found!": 826, "dracut module 'pcsc' will not be installed, because command 'pcscd' could not be found!": 827, "dracut module 'cifs' will not be installed, because command 'mount.cifs' could not be found!": 828, "95nfs: Could not find any command of 'rpcbind portmap'!": 829, "dracut module 'biosdevname' will not be installed, because command 'biosdevname' could not be found!": 830, "dracut module 'masterkey' will not be installed, because command 'keyctl' could not be found!": 831, "dracut module 'memstrack' will not be installed, because command 'memstrack' could not be found!": 832, "memstrack is not available": 833, "If you need to use rd.memdebug>=4, please install memstrack and procps-ng": 834, "*** Including module: bash ***": 835, "*** Including module: systemd ***": 836, "*** Including module: systemd-initrd ***": 837, "*** Including module: systemd-sysusers ***": 838, "*** Including module: nss-softokn ***": 839, "*** Including module: dbus-broker ***": 840, "*** Including module: dbus ***": 841, "*** Including module: i18n ***": 842, "*** Including module: network-manager ***": 843, "*** Including module: network ***": 844, "*** Including module: ifcfg ***": 845, "*** Including module: drm ***": 846, "*** Including module: plymouth ***": 847, "*** Including module: prefixdevname ***": 848, "*** Including module: dm ***": 849, "Skipping udev rule: 64-device-mapper.rules": 850, "Skipping udev rule: 60-persistent-storage-dm.rules": 851, "Skipping udev rule: 55-dm.rules": 852, "*** Including module: kernel-modules ***": 853, "*** Including module: kernel-modules-extra ***": 854, "  kernel-modules-extra: configuration source \"*\" does not exist": 855, "  kernel-modules-extra: parsing configuration file \"*\"": 856, "  kernel-modules-extra: *: added \"updates extra built-in weak-updates\" to the list of search directories": 857, "  kernel-modules-extra: *: override \"kvdo 5.14.0-427.el9.* weak-updates*\" is ignored since \"5.14.0-427.el9.*\" doesn't match \"5.14.0-427.22.1.el9_4.x86_64\"": 858, "*** Including module: kernel-network-modules ***": 859, "*** Including module: lvm ***": 860, "Skipping udev rule: 56-lvm.rules": 861, "Skipping udev rule: 60-persistent-storage-lvm.rules": 862, "*** Including module: resume ***": 863, "*** Including module: rootfs-block ***": 864, "*** Including module: terminfo ***": 865, "*** Including module: udev-rules ***": 866, "Skipping udev rule: 91-permissions.rules": 867, "Skipping udev rule: 80-drivers-modprobe.rules": 868, "Skipping udev rule: 70-persistent-net.rules": 869, "*** Including module: dracut-systemd ***": 870, "*** Including module: usrmount ***": 871, "*** Including module: base ***": 872, "*** Including module: fs-lib ***": 873, "*** Including module: microcode_ctl-fw_dir_override ***": 874, "  microcode_ctl module: mangling fw_dir": 875, "    microcode_ctl: reset fw_dir to \"* *\"": 876, "    microcode_ctl: processing data directory  \"*\"...": 877, "    microcode_ctl: configuration \"intel\" is ignored": 878, "    microcode_ctl: configuration \"intel-06-2d-07\" is ignored": 879, "    microcode_ctl: configuration \"intel-06-4e-03\" is ignored": 880, "    microcode_ctl: configuration \"intel-06-4f-01\" is ignored": 881, "    microcode_ctl: configuration \"intel-06-55-04\" is ignored": 882, "    microcode_ctl: configuration \"intel-06-5e-03\" is ignored": 883, "      microcode_ctl: intel-06-8c-01: caveats check for kernel version \"5.14.0-427.22.1.el9_4.x86_64\" passed, adding \"*\" to fw_dir variable": 884, "    microcode_ctl: configuration \"intel-06-8e-9e-0x-0xca\" is ignored": 885, "    microcode_ctl: configuration \"intel-06-8e-9e-0x-dell\" is ignored": 886, "    microcode_ctl: final fw_dir: \"* * *\"": 887, "*** Including module: shutdown ***": 888, "*** Including modules done ***": 889, "*** Installing kernel module dependencies ***": 890, "*** Installing kernel module dependencies done ***": 891, "*** Resolving executable dependencies ***": 892, "*** Resolving executable dependencies done ***": 893, "*** Hardlinking files ***": 894, "Mode:           real": 895, "Files:          1790": 896, "Linked:         15 files": 897, "Compared:       0 xattrs": 898, "Compared:       433 files": 899, "Saved:          46.51 KiB": 900, "Duration:       0.195996 seconds": 901, "*** Hardlinking files done ***": 902, "*** Generating early-microcode cpio image ***": 903, "*** Constructing GenuineIntel.bin ***": 904, "*** Store current command line parameters ***": 905, "*** Stripping files ***": 906, "*** Stripping files done ***": 907, "*** Creating image file '*' ***": 908, "dracut: using auto-determined compression method 'pigz'": 909, "Image: *: 64M": 910, "========================================================================": 911, "Early CPIO image": 912, "drwxr-xr-x   3 root     root            0 Apr  7 21:06 .": 913, "-rw-r--r--   1 root     root            2 Apr  7 21:06 early_cpio": 914, "drwxr-xr-x   3 root     root            0 Apr  7 21:06 kernel": 915, "drwxr-xr-x   3 root     root            0 Apr  7 21:06 kernel*": 916, "drwxr-xr-x   2 root     root            0 Apr  7 21:06 kernel*": 917, "-rw-r--r--   1 root     root       111616 Apr  7 21:06 kernel*": 918, "Version:": 919, "Arguments:  -f": 920, "dracut modules:": 921, "bash": 922, "systemd": 923, "systemd-initrd": 924, "systemd-sysusers": 925, "nss-softokn": 926, "dbus-broker": 927, "dbus": 928, "i18n": 929, "network-manager": 930, "network": 931, "ifcfg": 932, "drm": 